LICENSE
README.md
setup.cfg
setup.py
atmega/__init__.py
atmega/command.py
atmega/ram.py
atmega.egg-info/PKG-INFO
atmega.egg-info/SOURCES.txt
atmega.egg-info/dependency_links.txt
atmega.egg-info/requires.txt
atmega.egg-info/top_level.txt
tests/__init__.py
tests/device_communication.py