Metadata-Version: 2.1
Name: atmega
Version: 0.0.2
Summary: Provides an API for atmega devices (memory manipulation)
Home-page: https://github.com/CEA-IM2AG/ATMEGA-API
Author: Sofiane DJERBI, Ny Aina PEDERSEN, Aymes FREZJA, Nour LADHARI, Yanis ACHAICHIA, Amine OTMANE
Author-email: sofiane.djerbi@etu.univ-grenoble-alpes.fr
License: UNKNOWN
Keywords: API,development,FTDI,RS232,USB,Serial
Platform: UNKNOWN
Classifier: Intended Audience :: Developers
Classifier: Development Status :: 5 - Production/Stable
Classifier: Programming Language :: Python :: 3
Classifier: Programming Language :: Python :: 3.7
Classifier: Programming Language :: Python :: 3.8
Classifier: Programming Language :: Python :: 3.9
Classifier: Programming Language :: Python :: 3.10
Classifier: Programming Language :: Python :: 3 :: Only
Classifier: Topic :: System :: Hardware :: Universal Serial Bus (USB)
Classifier: License :: OSI Approved :: GNU General Public License v3 (GPLv3)
License-File: LICENSE
